[{"nombre":"Pepe","apellido":"Luis","edad":55,"domicilio":{"calle":"Calle Falsa","numero":123},"fechaNacimiento":"1972-01-15","telefonos":[{"@type":"TelefonoFijo","numero":"4588754","codArea":"223","codPais":"549"},{"@type":"TelefonoCelular","numero":"155478598","codArea":"2234","codPais":"548","usaWhatsapp":true}]},{"nombre":"Pepe Dos","apellido":"Luis","edad":55,"domicilio":{"calle":"Calle Falsa","numero":123},"fechaNacimiento":"1990-10-01","telefonos":[{"@type":"TelefonoFijo","numero":"4588754","codArea":"223","codPais":"549"},{"@type":"TelefonoFijo","numero":"155478598","codArea":"2234","codPais":"548"}]}]